Metadata-Version: 2.1
Name: nplocate
Version: 0.2.7
Summary: Python tools to locate nano particles from confocal microscope images
Home-page: https://github.com/yangyushi/nplocate
Author: Yushi Yang
Author-email: yangyushi1992@icloud.com
License: UNKNOWN
Platform: UNKNOWN
Classifier: Programming Language :: Python
Classifier: Operating System :: OS Independent
